identities/__init__.py
identities/admin.py
identities/models.py
identities/serializers.py
identities/tasks.py
identities/tests.py
identities/urls.py
identities/views.py
identities/migrations/0001_initial.py
identities/migrations/0002_auto_20160204_1427.py
identities/migrations/0003_optout.py
identities/migrations/0004_detailkey.py
identities/migrations/0005_optin.py
identities/migrations/0006_identity_failed_message_count.py
identities/migrations/0007_auto_20170713_1704.py
identities/migrations/0008_auto_20181213_1443.py
identities/migrations/0009_auto_20190201_1506.py
identities/migrations/__init__.py
identities/templatetags/__init__.py
identities/templatetags/seed.py
seed_identity_store/__init__.py
seed_identity_store/auth.py
seed_identity_store/celery.py
seed_identity_store/decorators.py
seed_identity_store/settings.py
seed_identity_store/test_decorators.py
seed_identity_store/testsettings.py
seed_identity_store/urls.py
seed_identity_store/wsgi.py
seed_identity_store-0.10.3.dist-info/LICENCE
seed_identity_store-0.10.3.dist-info/METADATA
seed_identity_store-0.10.3.dist-info/WHEEL
seed_identity_store-0.10.3.dist-info/top_level.txt
seed_identity_store-0.10.3.dist-info/RECORD
